food/__init__.py
food-0.0.11.dist-info/LICENCE
food-0.0.11.dist-info/METADATA
food-0.0.11.dist-info/WHEEL
food-0.0.11.dist-info/top_level.txt
food-0.0.11.dist-info/RECORD
